geometricjax_experimental/__init__.py
geometricjax_experimental/pg.py
geometricjax_experimental-0.3.0.dist-info/METADATA
geometricjax_experimental-0.3.0.dist-info/WHEEL
geometricjax_experimental-0.3.0.dist-info/licenses/LICENSE
geometricjax_experimental-0.3.0.dist-info/RECORD
