Metadata-Version: 2.3
Name: geometricjax_experimental
Version: 0.3.0
Summary: basic tests for full geometricjax library
Project-URL: repository, https://github.com/samir539/geometricjax_experimental
Author-email: samir539 <github.emails.13@gmail.com>
License:             Apache License
License-File: LICENSE
Keywords: deep-learning,jax,neural-networks
Classifier: Development Status :: 3 - Alpha
Classifier: Intended Audience :: Developers
Classifier: Intended Audience :: Financial and Insurance Industry
Classifier: Intended Audience :: Information Technology
Classifier: Intended Audience :: Science/Research
Classifier: License :: OSI Approved :: Apache Software License
Classifier: Natural Language :: English
Classifier: Programming Language :: Python :: 3
Classifier: Topic :: Scientific/Engineering :: Artificial Intelligence
Classifier: Topic :: Scientific/Engineering :: Information Analysis
Classifier: Topic :: Scientific/Engineering :: Mathematics
Requires-Python: ~=3.9
Requires-Dist: jax!=0.4.27,>=0.4.13
Requires-Dist: jaxtyping>=0.2.20
Requires-Dist: typing-extensions>=4.5.0
